python2c2p
